<?xml version="1.0" encoding="UTF-8"?>
<objects serializationModel="Studio.02.02.00">
	<object class="ParameterPreset" id="{03372929-4c9d-41a3-a669-5a7adc69f687}">
		<property name="name">
			<value>intensity_brass1</value>
		</property>
		<relationship name="folder">
			<destination>{e489e1da-938d-42d9-ae22-290f671eb64f}</destination>
		</relationship>
		<relationship name="parameter">
			<destination>{03a94ef2-e203-4197-9d25-1aa737a0a1fb}</destination>
		</relationship>
	</object>
	<object class="GameParameter" id="{03a94ef2-e203-4197-9d25-1aa737a0a1fb}">
		<property name="initialValue">
			<value>0</value>
		</property>
		<property name="seekSpeed">
			<value>0.23999999463558197</value>
		</property>
	</object>
</objects>
